twotter/__init__.py
twotter/twotter.json
twotter/twotter.py
twotter-0.1.0.dist-info/DESCRIPTION.rst
twotter-0.1.0.dist-info/entry_points.txt
twotter-0.1.0.dist-info/METADATA
twotter-0.1.0.dist-info/metadata.json
twotter-0.1.0.dist-info/RECORD
twotter-0.1.0.dist-info/top_level.txt
twotter-0.1.0.dist-info/WHEEL
