Metadata-Version: 2.0
Name: twotter
Version: 0.1.0
Summary: Scrapes BAS Air Unit asset locations
Home-page: https://github.com/kenners/twotter
Author: Kenrick Turner
Author-email: kenrickturner@gmail.com
License: MIT
Keywords: scraping json antarctica aircraft latitude
Platform: UNKNOWN
Classifier: Development Status :: 3 - Alpha
Classifier: Intended Audience :: Developers
Classifier: License :: OSI Approved :: MIT License
Classifier: Programming Language :: Python :: 3.3
Classifier: Programming Language :: Python :: 3.4
Requires-Dist: simplejson (>=3.5.2)
Requires-Dist: requests (>=2.4.3)
Requires-Dist: basemap (>=1.0.7)
Requires-Dist: matplotlib (>=1.3.1)
Requires-Dist: numpy (>=1.8.1)
